indonesian_number_normalizer/__init__.py
indonesian_number_normalizer/constants.py
indonesian_number_normalizer/normalizer.py
indonesian_number_normalizer-0.1.1.dist-info/LICENSE
indonesian_number_normalizer-0.1.1.dist-info/METADATA
indonesian_number_normalizer-0.1.1.dist-info/WHEEL
indonesian_number_normalizer-0.1.1.dist-info/top_level.txt
indonesian_number_normalizer-0.1.1.dist-info/RECORD
