Metadata-Version: 2.1
Name: indonesian-number-normalizer
Version: 0.1.1
Summary: A package to convert numbers to Indonesian words
Home-page: https://github.com/fiddien/indonesian-number-normalizer
Author: Ilma Aliya Fiddien
Author-email: Ilma Aliya Fiddien <ilmaaliyaf@gmail.com>
License: MIT License
Requires-Python: >=3.7
License-File: LICENSE
Provides-Extra: test
Requires-Dist: pytest>=6.0; extra == "test"
Requires-Dist: pytest-cov>=2.0; extra == "test"
